<annotation>
	<folder>efsb</folder>
	<filename>362.jpg</filename>
	<path>C:\Users\aaron\Documents\github\EFSB_Tracking_Image_Repository\OID\Dataset\train\efsb\362.jpg</path>
	<source>
		<database>Unknown</database>
	</source>
	<size>
		<width>1920</width>
		<height>1080</height>
		<depth>3</depth>
	</size>
	<segmented>0</segmented>
	<object>
		<name>efsb</name>
		<pose>Unspecified</pose>
		<truncated>0</truncated>
		<difficult>0</difficult>
		<bndbox>
			<xmin>306</xmin>
			<ymin>107</ymin>
			<xmax>416</xmax>
			<ymax>156</ymax>
		</bndbox>
	</object>
	<object>
		<name>efsb</name>
		<pose>Unspecified</pose>
		<truncated>0</truncated>
		<difficult>0</difficult>
		<bndbox>
			<xmin>236</xmin>
			<ymin>341</ymin>
			<xmax>358</xmax>
			<ymax>394</ymax>
		</bndbox>
	</object>
	<object>
		<name>efsb</name>
		<pose>Unspecified</pose>
		<truncated>0</truncated>
		<difficult>0</difficult>
		<bndbox>
			<xmin>352</xmin>
			<ymin>579</ymin>
			<xmax>448</xmax>
			<ymax>646</ymax>
		</bndbox>
	</object>
	<object>
		<name>efsb</name>
		<pose>Unspecified</pose>
		<truncated>0</truncated>
		<difficult>0</difficult>
		<bndbox>
			<xmin>277</xmin>
			<ymin>565</ymin>
			<xmax>343</xmax>
			<ymax>601</ymax>
		</bndbox>
	</object>
	<object>
		<name>efsb</name>
		<pose>Unspecified</pose>
		<truncated>0</truncated>
		<difficult>0</difficult>
		<bndbox>
			<xmin>849</xmin>
			<ymin>815</ymin>
			<xmax>897</xmax>
			<ymax>921</ymax>
		</bndbox>
	</object>
</annotation>
