<annotation>
	<folder>final_rename</folder>
	<filename>174.jpg</filename>
	<path>C:\Users\aaron\Pictures\SP\final_rename\174.jpg</path>
	<source>
		<database>Unknown</database>
	</source>
	<size>
		<width>1920</width>
		<height>1080</height>
		<depth>3</depth>
	</size>
	<segmented>0</segmented>
	<object>
		<name>eggplant</name>
		<pose>Unspecified</pose>
		<truncated>0</truncated>
		<difficult>0</difficult>
		<bndbox>
			<xmin>454</xmin>
			<ymin>107</ymin>
			<xmax>692</xmax>
			<ymax>345</ymax>
		</bndbox>
	</object>
	<object>
		<name>eggplant</name>
		<pose>Unspecified</pose>
		<truncated>0</truncated>
		<difficult>0</difficult>
		<bndbox>
			<xmin>1226</xmin>
			<ymin>130</ymin>
			<xmax>1447</xmax>
			<ymax>350</ymax>
		</bndbox>
	</object>
	<object>
		<name>eggplant</name>
		<pose>Unspecified</pose>
		<truncated>0</truncated>
		<difficult>0</difficult>
		<bndbox>
			<xmin>1178</xmin>
			<ymin>765</ymin>
			<xmax>1412</xmax>
			<ymax>990</ymax>
		</bndbox>
	</object>
	<object>
		<name>eggplant</name>
		<pose>Unspecified</pose>
		<truncated>0</truncated>
		<difficult>0</difficult>
		<bndbox>
			<xmin>483</xmin>
			<ymin>746</ymin>
			<xmax>721</xmax>
			<ymax>999</ymax>
		</bndbox>
	</object>
	<object>
		<name>efsb</name>
		<pose>Unspecified</pose>
		<truncated>0</truncated>
		<difficult>0</difficult>
		<bndbox>
			<xmin>528</xmin>
			<ymin>934</ymin>
			<xmax>619</xmax>
			<ymax>974</ymax>
		</bndbox>
	</object>
	<object>
		<name>efsb</name>
		<pose>Unspecified</pose>
		<truncated>0</truncated>
		<difficult>0</difficult>
		<bndbox>
			<xmin>447</xmin>
			<ymin>200</ymin>
			<xmax>479</xmax>
			<ymax>284</ymax>
		</bndbox>
	</object>
	<object>
		<name>efsb</name>
		<pose>Unspecified</pose>
		<truncated>0</truncated>
		<difficult>0</difficult>
		<bndbox>
			<xmin>457</xmin>
			<ymin>250</ymin>
			<xmax>497</xmax>
			<ymax>327</ymax>
		</bndbox>
	</object>
	<object>
		<name>efsb</name>
		<pose>Unspecified</pose>
		<truncated>0</truncated>
		<difficult>0</difficult>
		<bndbox>
			<xmin>476</xmin>
			<ymin>291</ymin>
			<xmax>547</xmax>
			<ymax>336</ymax>
		</bndbox>
	</object>
	<object>
		<name>efsb</name>
		<pose>Unspecified</pose>
		<truncated>0</truncated>
		<difficult>0</difficult>
		<bndbox>
			<xmin>1374</xmin>
			<ymin>184</ymin>
			<xmax>1417</xmax>
			<ymax>230</ymax>
		</bndbox>
	</object>
</annotation>
