<annotation>
	<folder>final_rename</folder>
	<filename>423.jpg</filename>
	<path>C:\Users\aaron\Pictures\SP\final_rename\423.jpg</path>
	<source>
		<database>Unknown</database>
	</source>
	<size>
		<width>1920</width>
		<height>1080</height>
		<depth>3</depth>
	</size>
	<segmented>0</segmented>
	<object>
		<name>efsb</name>
		<pose>Unspecified</pose>
		<truncated>0</truncated>
		<difficult>0</difficult>
		<bndbox>
			<xmin>63</xmin>
			<ymin>72</ymin>
			<xmax>194</xmax>
			<ymax>110</ymax>
		</bndbox>
	</object>
	<object>
		<name>efsb</name>
		<pose>Unspecified</pose>
		<truncated>0</truncated>
		<difficult>0</difficult>
		<bndbox>
			<xmin>91</xmin>
			<ymin>311</ymin>
			<xmax>211</xmax>
			<ymax>349</ymax>
		</bndbox>
	</object>
	<object>
		<name>efsb</name>
		<pose>Unspecified</pose>
		<truncated>0</truncated>
		<difficult>0</difficult>
		<bndbox>
			<xmin>279</xmin>
			<ymin>585</ymin>
			<xmax>391</xmax>
			<ymax>610</ymax>
		</bndbox>
	</object>
	<object>
		<name>efsb</name>
		<pose>Unspecified</pose>
		<truncated>0</truncated>
		<difficult>0</difficult>
		<bndbox>
			<xmin>168</xmin>
			<ymin>519</ymin>
			<xmax>273</xmax>
			<ymax>574</ymax>
		</bndbox>
	</object>
	<object>
		<name>efsb</name>
		<pose>Unspecified</pose>
		<truncated>0</truncated>
		<difficult>0</difficult>
		<bndbox>
			<xmin>834</xmin>
			<ymin>847</ymin>
			<xmax>877</xmax>
			<ymax>946</ymax>
		</bndbox>
	</object>
	<object>
		<name>eggplant</name>
		<pose>Unspecified</pose>
		<truncated>0</truncated>
		<difficult>0</difficult>
		<bndbox>
			<xmin>152</xmin>
			<ymin>482</ymin>
			<xmax>336</xmax>
			<ymax>655</ymax>
		</bndbox>
	</object>
	<object>
		<name>eggplant</name>
		<pose>Unspecified</pose>
		<truncated>1</truncated>
		<difficult>0</difficult>
		<bndbox>
			<xmin>763</xmin>
			<ymin>1</ymin>
			<xmax>1001</xmax>
			<ymax>154</ymax>
		</bndbox>
	</object>
	<object>
		<name>eggplant</name>
		<pose>Unspecified</pose>
		<truncated>1</truncated>
		<difficult>0</difficult>
		<bndbox>
			<xmin>718</xmin>
			<ymin>905</ymin>
			<xmax>1022</xmax>
			<ymax>1080</ymax>
		</bndbox>
	</object>
	<object>
		<name>eggplant</name>
		<pose>Unspecified</pose>
		<truncated>0</truncated>
		<difficult>0</difficult>
		<bndbox>
			<xmin>1398</xmin>
			<ymin>476</ymin>
			<xmax>1588</xmax>
			<ymax>670</ymax>
		</bndbox>
	</object>
</annotation>
